{
    "LoginOrgs":{
        "LoginOrg":[
            {
                "ID": 1000908060000097,
                "Code": "001",
                "Name": "浙江永强集团股份有限公司"
             },
                {
                "ID": 1000908060000721,
                "Code": 101,
                "Name": "台州永强工艺品有限公司"
             },
                {
                "ID": 1000908060000735,
                "Code": 102,
                "Name": "临海市英仕达遮阳制品有限公司"
             },
                {
                "ID": 1000908060000743,
                "Code": 103,
                "Name": "宁波花园旅游用品有限公司"
             },
                {
                "ID": 1000908060000763,
                "Code": 104,
                "Name": "宁波杰倍德日用品有限公司"
             },
                {
                "ID": 1000908060001049,
                "Code": 105,
                "Name": "永强户外用品(宁波)有限公司"
             },
                {
                "ID": 1005307093911747,
                "Code": 108,
                "Name": "宁波永宏户外休闲用品有限公司"
             },
                {
                "ID": 1005307093913653,
                "Code": 109,
                "Name": "宁波强邦户外休闲用品有限公司"
             },
                {
                "ID": 1005503252715442,
                "Code": 110,
                "Name": "浙江永强集团股份有限公司厦门分公司"
             },
                {
                "ID": 1005907147828798,
                "Code": 111,
                "Name": "浙江临海永强股权并购投资中心（有限合伙）"
             },
                {
                "ID": 1006108097354826,
                "Code": 112,
                "Name": "山东永旭户外休闲用品有限公司"
             },
                {
                "ID": 1006201309243967,
                "Code": 113,
                "Name": "浙江尚匠智能家居有限公司"
             },
                {
                "ID": 1006301219520524,
                "Code": 114,
                "Name": "宁波浙科永强创业投资合伙企业（有限合伙）"
             },
                {
                "ID": 1004910239461105,
                "Code": 301,
                "Name": "制造一部"
             },
                {
                "ID": 1004910239462613,
                "Code": 302,
                "Name": "制造二部"
             },
                {
                "ID": 1004910239464081,
                "Code": 303,
                "Name": "制造三部"
             },
                {
                "ID": 1004910239465531,
                "Code": 304,
                "Name": "制造四部"
             },
                {
                "ID": 1004910239469970,
                "Code": 305,
                "Name": "制造五部"
             },
                {
                "ID": 1004910239468428,
                "Code": 306,
                "Name": "塑料厂"
             },
                {
                "ID": 1005505149145228,
                "Code": 307,
                "Name": "制造十部"
             },
                {
                "ID": 1005603136750690,
                "Code": 308,
                "Name": "冲件部（失效）"
             },
                {
                "ID": 1005704030634852,
                "Code": 309,
                "Name": "制造五部（英仕达厂区）"
             },
                {
                "ID": 1005804219704955,
                "Code": 310,
                "Name": "浙江永信检测技术有限公司"
             },
                {
                "ID": 1005805174730093,
                "Code": 311,
                "Name": "临海永金管业有限公司"
             },
                {
                "ID": 1005806279058736,
                "Code": 312,
                "Name": "上海优享家居有限公司"
             },
                {
                "ID": 1006003041378705,
                "Code": 313,
                "Name": "临海市永强投资有限公司"
             },
                {
                "ID": 1006004010335353,
                "Code": 314,
                "Name": "浙江永强石英科技发展股份有限公司"
             },
                {
                "ID": 1006012092295568,
                "Code": 315,
                "Name": "上海寓悦科技有限公司"
             },
                {
                "ID": 1006012218330932,
                "Code": 316,
                "Name": "上海齐家永强户外用品有限公司"
             },
                {
                "ID": 1006101234781378,
                "Code": 317,
                "Name": "北京联拓天际电子商务有限公司"
             },
                {
                "ID": 1006101234783983,
                "Code": 318,
                "Name": "北京九州之旅科贸有限责任公司"
             },
                {
                "ID": 1006101234785868,
                "Code": 319,
                "Name": "北京联拓天下旅行社有限公司"
             },
                {
                "ID": 1006101234787694,
                "Code": 320,
                "Name": "合肥联拓天际电子商务有限公司"
             },
                {
                "ID": 1006108077882143,
                "Code": 321,
                "Name": "北京中航易购信息服务有限公司"
             },
                {
                "ID": 1006202080565824,
                "Code": 322,
                "Name": "上海先临投资有限公司"
             },
                {
                "ID": 1006202080567429,
                "Code": 323,
                "Name": "上海永强鸿坤资产经营中心（有限合伙）"
             },
                {
                "ID": 1006202196673201,
                "Code": 324,
                "Name": "冲件部"
             },
                {
                "ID": 1006202210218563,
                "Code": 325,
                "Name": "技术部"
             },
                {
                "ID": 1006204050042875,
                "Code": 326,
                "Name": "合肥三分网络科技有限公司"
             },
                {
                "ID": 1006305289894688,
                "Code": 327,
                "Name": "制造十一部"
             },
                {
                "ID": 1006305289898837,
                "Code": 328,
                "Name": "制造十二部"
             },
                {
                "ID": 1006304079839049,
                "Code": 501,
                "Name": "浙江永强朗成房地产有限公司"
             },
                {
                "ID": 1006304079842489,
                "Code": 502,
                "Name": "台州朗成房地产开发有限公司"
             },
                {
                "ID": 1006304079844288,
                "Code": 503,
                "Name": "临海朗成商业经营管理有限公司"
             },
                {
                "ID": 1006304079846898,
                "Code": 504,
                "Name": "上海朗成房地产开发有限公司"
             },
                {
                "ID": 1006304079855279,
                "Code": 551,
                "Name": "浙江东都节能技术股份有限公司"
             },
                {
                "ID": 1006304079857276,
                "Code": 552,
                "Name": "嘉善东都节能技术有限公司"
             },
                {
                "ID": 1006304079859106,
                "Code": 553,
                "Name": "钟祥市东都节能有限公司"
             },
                {
                "ID": 1006304079860958,
                "Code": 554,
                "Name": "临海市科森热能设备有限公司"
             }
        ]
    }

}